{"model.embed_tokens.weight": {"offset": 0, "size": 525336576, "padded_size": 525336576, "shape": [128256, 2048], "dtype": "BF16", "transposed": false}, "model.layers.0.input_layernorm.weight": {"offset": 525336576, "size": 4096, "padded_size": 4096, "shape": [2048], "dtype": "BF16", "transposed": false}, "model.layers.0.self_attn.q_proj.weight": {"offset": 525340672, "size": 8388608, "padded_size": 8388608, "shape": [2048, 2048], "dtype": "BF16", "transposed": true}, "model.layers.0.self_attn.k_proj.weight": {"offset": 533729280, "size": 2097152, "padded_size": 2097152, "shape": [2048, 512], "dtype": "BF16", "transposed": true}, "model.layers.0.self_attn.v_proj.weight": {"offset": 535826432, "size": 2097152, "padded_size": 2097152, "shape": [2048, 512], "dtype": "BF16", "transposed": true}, "model.layers.0.self_attn.o_proj.weight": {"offset": 537923584, "size": 8388608, "padded_size": 8388608, "shape": [2048, 2048], "dtype": "BF16", "transposed": true}, "model.layers.0.post_attention_layernorm.weight": {"offset": 546312192, "size": 4096, "padded_size": 4096, "shape": [2048], "dtype": "BF16", "transposed": false}, "model.layers.0.mlp.down_proj.weight": {"offset": 546316288, "size": 33554432, "padded_size": 33554432, "shape": [8192, 2048], "dtype": "BF16", "transposed": true}, "model.layers.0.mlp.gate_proj.weight": {"offset": 579870720, "size": 33554432, "padded_size": 33554432, "shape": [2048, 8192], "dtype": "BF16", "transposed": true}, "model.layers.0.mlp.up_proj.weight": {"offset": 613425152, "size": 33554432, "padded_size": 33554432, "shape": [2048, 8192], "dtype": "BF16", "transposed": true}, "model.layers.1.input_layernorm.weight": {"offset": 646979584, "size": 4096, "padded_size": 4096, "shape": [2048], "dtype": "BF16", "transposed": false}, "model.layers.1.self_attn.q_proj.weight": {"offset": 646983680, "size": 8388608, "padded_size": 8388608, "shape": [2048, 2048], "dtype": "BF16", "transposed": true}, "model.layers.1.self_attn.k_proj.weight": {"offset": 655372288, "size": 2097152, "padded_size": 2097152, "shape": [2048, 512], "dtype": "BF16", "transposed": true}, "model.layers.1.self_attn.v_proj.weight": {"offset": 657469440, "size": 2097152, "padded_size": 2097152, "shape": [2048, 512], "dtype": "BF16", "transposed": true}, "model.layers.1.self_attn.o_proj.weight": {"offset": 659566592, "size": 8388608, "padded_size": 8388608, "shape": [2048, 2048], "dtype": "BF16", "transposed": true}, "model.layers.1.post_attention_layernorm.weight": {"offset": 667955200, "size": 4096, "padded_size": 4096, "shape": [2048], "dtype": "BF16", "transposed": false}, "model.layers.1.mlp.down_proj.weight": {"offset": 667959296, "size": 33554432, "padded_size": 33554432, "shape": [8192, 2048], "dtype": "BF16", "transposed": true}, "model.layers.1.mlp.gate_proj.weight": {"offset": 701513728, "size": 33554432, "padded_size": 33554432, "shape": [2048, 8192], "dtype": "BF16", "transposed": true}, "model.layers.1.mlp.up_proj.weight": {"offset": 735068160, "size": 33554432, "padded_size": 33554432, "shape": [2048, 8192], "dtype": "BF16", "transposed": true}, "model.layers.2.input_layernorm.weight": {"offset": 768622592, "size": 4096, "padded_size": 4096, "shape": [2048], "dtype": "BF16", "transposed": false}, "model.layers.2.self_attn.q_proj.weight": {"offset": 768626688, "size": 8388608, "padded_size": 8388608, "shape": [2048, 2048], "dtype": "BF16", "transposed": true}, "model.layers.2.self_attn.k_proj.weight": {"offset": 777015296, "size": 2097152, "padded_size": 2097152, "shape": [2048, 512], "dtype": "BF16", "transposed": true}, "model.layers.2.self_attn.v_proj.weight": {"offset": 779112448, "size": 2097152, "padded_size": 2097152, "shape": [2048, 512], "dtype": "BF16", "transposed": true}, "model.layers.2.self_attn.o_proj.weight": {"offset": 781209600, "size": 8388608, "padded_size": 8388608, "shape": [2048, 2048], "dtype": "BF16", "transposed": true}, "model.layers.2.post_attention_layernorm.weight": {"offset": 789598208, "size": 4096, "padded_size": 4096, "shape": [2048], "dtype": "BF16", "transposed": false}, "model.layers.2.mlp.down_proj.weight": {"offset": 789602304, "size": 33554432, "padded_size": 33554432, "shape": [8192, 2048], "dtype": "BF16", "transposed": true}, "model.layers.2.mlp.gate_proj.weight": {"offset": 823156736, "size": 33554432, "padded_size": 33554432, "shape": [2048, 8192], "dtype": "BF16", "transposed": true}, "model.layers.2.mlp.up_proj.weight": {"offset": 856711168, "size": 33554432, "padded_size": 33554432, "shape": [2048, 8192], "dtype": "BF16", "transposed": true}, "model.layers.3.input_layernorm.weight": {"offset": 890265600, "size": 4096, "padded_size": 4096, "shape": [2048], "dtype": "BF16", "transposed": false}, "model.layers.3.self_attn.q_proj.weight": {"offset": 890269696, "size": 8388608, "padded_size": 8388608, "shape": [2048, 2048], "dtype": "BF16", "transposed": true}, "model.layers.3.self_attn.k_proj.weight": {"offset": 898658304, "size": 2097152, "padded_size": 2097152, "shape": [2048, 512], "dtype": "BF16", "transposed": true}, "model.layers.3.self_attn.v_proj.weight": {"offset": 900755456, "size": 2097152, "padded_size": 2097152, "shape": [2048, 512], "dtype": "BF16", "transposed": true}, "model.layers.3.self_attn.o_proj.weight": {"offset": 902852608, "size": 8388608, "padded_size": 8388608, "shape": [2048, 2048], "dtype": "BF16", "transposed": true}, "model.layers.3.post_attention_layernorm.weight": {"offset": 911241216, "size": 4096, "padded_size": 4096, "shape": [2048], "dtype": "BF16", "transposed": false}, "model.layers.3.mlp.down_proj.weight": {"offset": 911245312, "size": 33554432, "padded_size": 33554432, "shape": [8192, 2048], "dtype": "BF16", "transposed": true}, "model.layers.3.mlp.gate_proj.weight": {"offset": 944799744, "size": 33554432, "padded_size": 33554432, "shape": [2048, 8192], "dtype": "BF16", "transposed": true}, "model.layers.3.mlp.up_proj.weight": {"offset": 978354176, "size": 33554432, "padded_size": 33554432, "shape": [2048, 8192], "dtype": "BF16", "transposed": true}, "model.layers.4.input_layernorm.weight": {"offset": 1011908608, "size": 4096, "padded_size": 4096, "shape": [2048], "dtype": "BF16", "transposed": false}, "model.layers.4.self_attn.q_proj.weight": {"offset": 1011912704, "size": 8388608, "padded_size": 8388608, "shape": [2048, 2048], "dtype": "BF16", "transposed": true}, "model.layers.4.self_attn.k_proj.weight": {"offset": 1020301312, "size": 2097152, "padded_size": 2097152, "shape": [2048, 512], "dtype": "BF16", "transposed": true}, "model.layers.4.self_attn.v_proj.weight": {"offset": 1022398464, "size": 2097152, "padded_size": 2097152, "shape": [2048, 512], "dtype": "BF16", "transposed": true}, "model.layers.4.self_attn.o_proj.weight": {"offset": 1024495616, "size": 8388608, "padded_size": 8388608, "shape": [2048, 2048], "dtype": "BF16", "transposed": true}, "model.layers.4.post_attention_layernorm.weight": {"offset": 1032884224, "size": 4096, "padded_size": 4096, "shape": [2048], "dtype": "BF16", "transposed": false}, "model.layers.4.mlp.down_proj.weight": {"offset": 1032888320, "size": 33554432, "padded_size": 33554432, "shape": [8192, 2048], "dtype": "BF16", "transposed": true}, "model.layers.4.mlp.gate_proj.weight": {"offset": 1066442752, "size": 33554432, "padded_size": 33554432, "shape": [2048, 8192], "dtype": "BF16", "transposed": true}, "model.layers.4.mlp.up_proj.weight": {"offset": 1099997184, "size": 33554432, "padded_size": 33554432, "shape": [2048, 8192], "dtype": "BF16", "transposed": true}, "model.layers.5.input_layernorm.weight": {"offset": 1133551616, "size": 4096, "padded_size": 4096, "shape": [2048], "dtype": "BF16", "transposed": false}, "model.layers.5.self_attn.q_proj.weight": {"offset": 1133555712, "size": 8388608, "padded_size": 8388608, "shape": [2048, 2048], "dtype": "BF16", "transposed": true}, "model.layers.5.self_attn.k_proj.weight": {"offset": 1141944320, "size": 2097152, "padded_size": 2097152, "shape": [2048, 512], "dtype": "BF16", "transposed": true}, "model.layers.5.self_attn.v_proj.weight": {"offset": 1144041472, "size": 2097152, "padded_size": 2097152, "shape": [2048, 512], "dtype": "BF16", "transposed": true}, "model.layers.5.self_attn.o_proj.weight": {"offset": 1146138624, "size": 8388608, "padded_size": 8388608, "shape": [2048, 2048], "dtype": "BF16", "transposed": true}, "model.layers.5.post_attention_layernorm.weight": {"offset": 1154527232, "size": 4096, "padded_size": 4096, "shape": [2048], "dtype": "BF16", "transposed": false}, "model.layers.5.mlp.down_proj.weight": {"offset": 1154531328, "size": 33554432, "padded_size": 33554432, "shape": [8192, 2048], "dtype": "BF16", "transposed": true}, "model.layers.5.mlp.gate_proj.weight": {"offset": 1188085760, "size": 33554432, "padded_size": 33554432, "shape": [2048, 8192], "dtype": "BF16", "transposed": true}, "model.layers.5.mlp.up_proj.weight": {"offset": 1221640192, "size": 33554432, "padded_size": 33554432, "shape": [2048, 8192], "dtype": "BF16", "transposed": true}, "model.layers.6.input_layernorm.weight": {"offset": 1255194624, "size": 4096, "padded_size": 4096, "shape": [2048], "dtype": "BF16", "transposed": false}, "model.layers.6.self_attn.q_proj.weight": {"offset": 1255198720, "size": 8388608, "padded_size": 8388608, "shape": [2048, 2048], "dtype": "BF16", "transposed": true}, "model.layers.6.self_attn.k_proj.weight": {"offset": 1263587328, "size": 2097152, "padded_size": 2097152, "shape": [2048, 512], "dtype": "BF16", "transposed": true}, "model.layers.6.self_attn.v_proj.weight": {"offset": 1265684480, "size": 2097152, "padded_size": 2097152, "shape": [2048, 512], "dtype": "BF16", "transposed": true}, "model.layers.6.self_attn.o_proj.weight": {"offset": 1267781632, "size": 8388608, "padded_size": 8388608, "shape": [2048, 2048], "dtype": "BF16", "transposed": true}, "model.layers.6.post_attention_layernorm.weight": {"offset": 1276170240, "size": 4096, "padded_size": 4096, "shape": [2048], "dtype": "BF16", "transposed": false}, "model.layers.6.mlp.down_proj.weight": {"offset": 1276174336, "size": 33554432, "padded_size": 33554432, "shape": [8192, 2048], "dtype": "BF16", "transposed": true}, "model.layers.6.mlp.gate_proj.weight": {"offset": 1309728768, "size": 33554432, "padded_size": 33554432, "shape": [2048, 8192], "dtype": "BF16", "transposed": true}, "model.layers.6.mlp.up_proj.weight": {"offset": 1343283200, "size": 33554432, "padded_size": 33554432, "shape": [2048, 8192], "dtype": "BF16", "transposed": true}, "model.layers.7.input_layernorm.weight": {"offset": 1376837632, "size": 4096, "padded_size": 4096, "shape": [2048], "dtype": "BF16", "transposed": false}, "model.layers.7.self_attn.q_proj.weight": {"offset": 1376841728, "size": 8388608, "padded_size": 8388608, "shape": [2048, 2048], "dtype": "BF16", "transposed": true}, "model.layers.7.self_attn.k_proj.weight": {"offset": 1385230336, "size": 2097152, "padded_size": 2097152, "shape": [2048, 512], "dtype": "BF16", "transposed": true}, "model.layers.7.self_attn.v_proj.weight": {"offset": 1387327488, "size": 2097152, "padded_size": 2097152, "shape": [2048, 512], "dtype": "BF16", "transposed": true}, "model.layers.7.self_attn.o_proj.weight": {"offset": 1389424640, "size": 8388608, "padded_size": 8388608, "shape": [2048, 2048], "dtype": "BF16", "transposed": true}, "model.layers.7.post_attention_layernorm.weight": {"offset": 1397813248, "size": 4096, "padded_size": 4096, "shape": [2048], "dtype": "BF16", "transposed": false}, "model.layers.7.mlp.down_proj.weight": {"offset": 1397817344, "size": 33554432, "padded_size": 33554432, "shape": [8192, 2048], "dtype": "BF16", "transposed": true}, "model.layers.7.mlp.gate_proj.weight": {"offset": 1431371776, "size": 33554432, "padded_size": 33554432, "shape": [2048, 8192], "dtype": "BF16", "transposed": true}, "model.layers.7.mlp.up_proj.weight": {"offset": 1464926208, "size": 33554432, "padded_size": 33554432, "shape": [2048, 8192], "dtype": "BF16", "transposed": true}, "model.layers.8.input_layernorm.weight": {"offset": 1498480640, "size": 4096, "padded_size": 4096, "shape": [2048], "dtype": "BF16", "transposed": false}, "model.layers.8.self_attn.q_proj.weight": {"offset": 1498484736, "size": 8388608, "padded_size": 8388608, "shape": [2048, 2048], "dtype": "BF16", "transposed": true}, "model.layers.8.self_attn.k_proj.weight": {"offset": 1506873344, "size": 2097152, "padded_size": 2097152, "shape": [2048, 512], "dtype": "BF16", "transposed": true}, "model.layers.8.self_attn.v_proj.weight": {"offset": 1508970496, "size": 2097152, "padded_size": 2097152, "shape": [2048, 512], "dtype": "BF16", "transposed": true}, "model.layers.8.self_attn.o_proj.weight": {"offset": 1511067648, "size": 8388608, "padded_size": 8388608, "shape": [2048, 2048], "dtype": "BF16", "transposed": true}, "model.layers.8.post_attention_layernorm.weight": {"offset": 1519456256, "size": 4096, "padded_size": 4096, "shape": [2048], "dtype": "BF16", "transposed": false}, "model.layers.8.mlp.down_proj.weight": {"offset": 1519460352, "size": 33554432, "padded_size": 33554432, "shape": [8192, 2048], "dtype": "BF16", "transposed": true}, "model.layers.8.mlp.gate_proj.weight": {"offset": 1553014784, "size": 33554432, "padded_size": 33554432, "shape": [2048, 8192], "dtype": "BF16", "transposed": true}, "model.layers.8.mlp.up_proj.weight": {"offset": 1586569216, "size": 33554432, "padded_size": 33554432, "shape": [2048, 8192], "dtype": "BF16", "transposed": true}, "model.layers.9.input_layernorm.weight": {"offset": 1620123648, "size": 4096, "padded_size": 4096, "shape": [2048], "dtype": "BF16", "transposed": false}, "model.layers.9.self_attn.q_proj.weight": {"offset": 1620127744, "size": 8388608, "padded_size": 8388608, "shape": [2048, 2048], "dtype": "BF16", "transposed": true}, "model.layers.9.self_attn.k_proj.weight": {"offset": 1628516352, "size": 2097152, "padded_size": 2097152, "shape": [2048, 512], "dtype": "BF16", "transposed": true}, "model.layers.9.self_attn.v_proj.weight": {"offset": 1630613504, "size": 2097152, "padded_size": 2097152, "shape": [2048, 512], "dtype": "BF16", "transposed": true}, "model.layers.9.self_attn.o_proj.weight": {"offset": 1632710656, "size": 8388608, "padded_size": 8388608, "shape": [2048, 2048], "dtype": "BF16", "transposed": true}, "model.layers.9.post_attention_layernorm.weight": {"offset": 1641099264, "size": 4096, "padded_size": 4096, "shape": [2048], "dtype": "BF16", "transposed": false}, "model.layers.9.mlp.down_proj.weight": {"offset": 1641103360, "size": 33554432, "padded_size": 33554432, "shape": [8192, 2048], "dtype": "BF16", "transposed": true}, "model.layers.9.mlp.gate_proj.weight": {"offset": 1674657792, "size": 33554432, "padded_size": 33554432, "shape": [2048, 8192], "dtype": "BF16", "transposed": true}, "model.layers.9.mlp.up_proj.weight": {"offset": 1708212224, "size": 33554432, "padded_size": 33554432, "shape": [2048, 8192], "dtype": "BF16", "transposed": true}, "model.layers.10.input_layernorm.weight": {"offset": 1741766656, "size": 4096, "padded_size": 4096, "shape": [2048], "dtype": "BF16", "transposed": false}, "model.layers.10.self_attn.q_proj.weight": {"offset": 1741770752, "size": 8388608, "padded_size": 8388608, "shape": [2048, 2048], "dtype": "BF16", "transposed": true}, "model.layers.10.self_attn.k_proj.weight": {"offset": 1750159360, "size": 2097152, "padded_size": 2097152, "shape": [2048, 512], "dtype": "BF16", "transposed": true}, "model.layers.10.self_attn.v_proj.weight": {"offset": 1752256512, "size": 2097152, "padded_size": 2097152, "shape": [2048, 512], "dtype": "BF16", "transposed": true}, "model.layers.10.self_attn.o_proj.weight": {"offset": 1754353664, "size": 8388608, "padded_size": 8388608, "shape": [2048, 2048], "dtype": "BF16", "transposed": true}, "model.layers.10.post_attention_layernorm.weight": {"offset": 1762742272, "size": 4096, "padded_size": 4096, "shape": [2048], "dtype": "BF16", "transposed": false}, "model.layers.10.mlp.down_proj.weight": {"offset": 1762746368, "size": 33554432, "padded_size": 33554432, "shape": [8192, 2048], "dtype": "BF16", "transposed": true}, "model.layers.10.mlp.gate_proj.weight": {"offset": 1796300800, "size": 33554432, "padded_size": 33554432, "shape": [2048, 8192], "dtype": "BF16", "transposed": true}, "model.layers.10.mlp.up_proj.weight": {"offset": 1829855232, "size": 33554432, "padded_size": 33554432, "shape": [2048, 8192], "dtype": "BF16", "transposed": true}, "model.layers.11.input_layernorm.weight": {"offset": 1863409664, "size": 4096, "padded_size": 4096, "shape": [2048], "dtype": "BF16", "transposed": false}, "model.layers.11.self_attn.q_proj.weight": {"offset": 1863413760, "size": 8388608, "padded_size": 8388608, "shape": [2048, 2048], "dtype": "BF16", "transposed": true}, "model.layers.11.self_attn.k_proj.weight": {"offset": 1871802368, "size": 2097152, "padded_size": 2097152, "shape": [2048, 512], "dtype": "BF16", "transposed": true}, "model.layers.11.self_attn.v_proj.weight": {"offset": 1873899520, "size": 2097152, "padded_size": 2097152, "shape": [2048, 512], "dtype": "BF16", "transposed": true}, "model.layers.11.self_attn.o_proj.weight": {"offset": 1875996672, "size": 8388608, "padded_size": 8388608, "shape": [2048, 2048], "dtype": "BF16", "transposed": true}, "model.layers.11.post_attention_layernorm.weight": {"offset": 1884385280, "size": 4096, "padded_size": 4096, "shape": [2048], "dtype": "BF16", "transposed": false}, "model.layers.11.mlp.down_proj.weight": {"offset": 1884389376, "size": 33554432, "padded_size": 33554432, "shape": [8192, 2048], "dtype": "BF16", "transposed": true}, "model.layers.11.mlp.gate_proj.weight": {"offset": 1917943808, "size": 33554432, "padded_size": 33554432, "shape": [2048, 8192], "dtype": "BF16", "transposed": true}, "model.layers.11.mlp.up_proj.weight": {"offset": 1951498240, "size": 33554432, "padded_size": 33554432, "shape": [2048, 8192], "dtype": "BF16", "transposed": true}, "model.layers.12.input_layernorm.weight": {"offset": 1985052672, "size": 4096, "padded_size": 4096, "shape": [2048], "dtype": "BF16", "transposed": false}, "model.layers.12.self_attn.q_proj.weight": {"offset": 1985056768, "size": 8388608, "padded_size": 8388608, "shape": [2048, 2048], "dtype": "BF16", "transposed": true}, "model.layers.12.self_attn.k_proj.weight": {"offset": 1993445376, "size": 2097152, "padded_size": 2097152, "shape": [2048, 512], "dtype": "BF16", "transposed": true}, "model.layers.12.self_attn.v_proj.weight": {"offset": 1995542528, "size": 2097152, "padded_size": 2097152, "shape": [2048, 512], "dtype": "BF16", "transposed": true}, "model.layers.12.self_attn.o_proj.weight": {"offset": 1997639680, "size": 8388608, "padded_size": 8388608, "shape": [2048, 2048], "dtype": "BF16", "transposed": true}, "model.layers.12.post_attention_layernorm.weight": {"offset": 2006028288, "size": 4096, "padded_size": 4096, "shape": [2048], "dtype": "BF16", "transposed": false}, "model.layers.12.mlp.down_proj.weight": {"offset": 2006032384, "size": 33554432, "padded_size": 33554432, "shape": [8192, 2048], "dtype": "BF16", "transposed": true}, "model.layers.12.mlp.gate_proj.weight": {"offset": 2039586816, "size": 33554432, "padded_size": 33554432, "shape": [2048, 8192], "dtype": "BF16", "transposed": true}, "model.layers.12.mlp.up_proj.weight": {"offset": 2073141248, "size": 33554432, "padded_size": 33554432, "shape": [2048, 8192], "dtype": "BF16", "transposed": true}, "model.layers.13.input_layernorm.weight": {"offset": 2106695680, "size": 4096, "padded_size": 4096, "shape": [2048], "dtype": "BF16", "transposed": false}, "model.layers.13.self_attn.q_proj.weight": {"offset": 2106699776, "size": 8388608, "padded_size": 8388608, "shape": [2048, 2048], "dtype": "BF16", "transposed": true}, "model.layers.13.self_attn.k_proj.weight": {"offset": 2115088384, "size": 2097152, "padded_size": 2097152, "shape": [2048, 512], "dtype": "BF16", "transposed": true}, "model.layers.13.self_attn.v_proj.weight": {"offset": 2117185536, "size": 2097152, "padded_size": 2097152, "shape": [2048, 512], "dtype": "BF16", "transposed": true}, "model.layers.13.self_attn.o_proj.weight": {"offset": 2119282688, "size": 8388608, "padded_size": 8388608, "shape": [2048, 2048], "dtype": "BF16", "transposed": true}, "model.layers.13.post_attention_layernorm.weight": {"offset": 2127671296, "size": 4096, "padded_size": 4096, "shape": [2048], "dtype": "BF16", "transposed": false}, "model.layers.13.mlp.down_proj.weight": {"offset": 2127675392, "size": 33554432, "padded_size": 33554432, "shape": [8192, 2048], "dtype": "BF16", "transposed": true}, "model.layers.13.mlp.gate_proj.weight": {"offset": 2161229824, "size": 33554432, "padded_size": 33554432, "shape": [2048, 8192], "dtype": "BF16", "transposed": true}, "model.layers.13.mlp.up_proj.weight": {"offset": 2194784256, "size": 33554432, "padded_size": 33554432, "shape": [2048, 8192], "dtype": "BF16", "transposed": true}, "model.layers.14.input_layernorm.weight": {"offset": 2228338688, "size": 4096, "padded_size": 4096, "shape": [2048], "dtype": "BF16", "transposed": false}, "model.layers.14.self_attn.q_proj.weight": {"offset": 2228342784, "size": 8388608, "padded_size": 8388608, "shape": [2048, 2048], "dtype": "BF16", "transposed": true}, "model.layers.14.self_attn.k_proj.weight": {"offset": 2236731392, "size": 2097152, "padded_size": 2097152, "shape": [2048, 512], "dtype": "BF16", "transposed": true}, "model.layers.14.self_attn.v_proj.weight": {"offset": 2238828544, "size": 2097152, "padded_size": 2097152, "shape": [2048, 512], "dtype": "BF16", "transposed": true}, "model.layers.14.self_attn.o_proj.weight": {"offset": 2240925696, "size": 8388608, "padded_size": 8388608, "shape": [2048, 2048], "dtype": "BF16", "transposed": true}, "model.layers.14.post_attention_layernorm.weight": {"offset": 2249314304, "size": 4096, "padded_size": 4096, "shape": [2048], "dtype": "BF16", "transposed": false}, "model.layers.14.mlp.down_proj.weight": {"offset": 2249318400, "size": 33554432, "padded_size": 33554432, "shape": [8192, 2048], "dtype": "BF16", "transposed": true}, "model.layers.14.mlp.gate_proj.weight": {"offset": 2282872832, "size": 33554432, "padded_size": 33554432, "shape": [2048, 8192], "dtype": "BF16", "transposed": true}, "model.layers.14.mlp.up_proj.weight": {"offset": 2316427264, "size": 33554432, "padded_size": 33554432, "shape": [2048, 8192], "dtype": "BF16", "transposed": true}, "model.layers.15.input_layernorm.weight": {"offset": 2349981696, "size": 4096, "padded_size": 4096, "shape": [2048], "dtype": "BF16", "transposed": false}, "model.layers.15.self_attn.q_proj.weight": {"offset": 2349985792, "size": 8388608, "padded_size": 8388608, "shape": [2048, 2048], "dtype": "BF16", "transposed": true}, "model.layers.15.self_attn.k_proj.weight": {"offset": 2358374400, "size": 2097152, "padded_size": 2097152, "shape": [2048, 512], "dtype": "BF16", "transposed": true}, "model.layers.15.self_attn.v_proj.weight": {"offset": 2360471552, "size": 2097152, "padded_size": 2097152, "shape": [2048, 512], "dtype": "BF16", "transposed": true}, "model.layers.15.self_attn.o_proj.weight": {"offset": 2362568704, "size": 8388608, "padded_size": 8388608, "shape": [2048, 2048], "dtype": "BF16", "transposed": true}, "model.layers.15.post_attention_layernorm.weight": {"offset": 2370957312, "size": 4096, "padded_size": 4096, "shape": [2048], "dtype": "BF16", "transposed": false}, "model.layers.15.mlp.down_proj.weight": {"offset": 2370961408, "size": 33554432, "padded_size": 33554432, "shape": [8192, 2048], "dtype": "BF16", "transposed": true}, "model.layers.15.mlp.gate_proj.weight": {"offset": 2404515840, "size": 33554432, "padded_size": 33554432, "shape": [2048, 8192], "dtype": "BF16", "transposed": true}, "model.layers.15.mlp.up_proj.weight": {"offset": 2438070272, "size": 33554432, "padded_size": 33554432, "shape": [2048, 8192], "dtype": "BF16", "transposed": true}, "model.norm.weight": {"offset": 2471624704, "size": 4096, "padded_size": 4096, "shape": [2048], "dtype": "BF16", "transposed": false}}